qiskit_alt/Project.toml
qiskit_alt/__init__.py
qiskit_alt/e_struct_julia.py
qiskit_alt/e_struct_python.py
qiskit_alt/electronic_structure.jl
qiskit_alt/electronic_structure.py
qiskit_alt/julia_project.py
qiskit_alt/juliacall_util.jl
qiskit_alt/pauli_operators.py
qiskit_alt/sys_image/Project.toml
qiskit_alt/sys_image/compile_exercise_script.jl
qiskit_alt/sys_image/packages.jl
qiskit_alt-0.1.13.dist-info/LICENSE.txt
qiskit_alt-0.1.13.dist-info/METADATA
qiskit_alt-0.1.13.dist-info/WHEEL
qiskit_alt-0.1.13.dist-info/top_level.txt
qiskit_alt-0.1.13.dist-info/RECORD
