Metadata-Version: 2.1
Name: qiskit-alt
Version: 0.1.13
Summary: Julia backend for Qiskit
License: Apache
Platform: UNKNOWN
Classifier: Framework :: Django
Classifier: License :: OSI Approved :: Apache Software License
Classifier: Programming Language :: Python :: 3
License-File: LICENSE.txt
Requires-Dist: pyscf (>=2.0)
Requires-Dist: julia
Requires-Dist: juliacall
Requires-Dist: qiskit-terra (>=0.19)
Requires-Dist: qiskit-nature (>=0.2)
Requires-Dist: julia-project (>=0.1.26)
Requires-Dist: ipywidgets
